ecmpy/00.Model_preview.ipynb
ecmpy/01.get_reactiion_kcat_using_DLKcat.ipynb
ecmpy/01.get_reaction_kcat_using_AutoPACMEN.ipynb
ecmpy/02.get_ecModel_using_ECMpy.ipynb
ecmpy/03.ecModel_calibration.ipynb
ecmpy/04.ecModel_analysis.ipynb
ecmpy/05.ecModel_ME.ipynb
ecmpy/06.One-click_modeling.ipynb
ecmpy/AutoPACMEN_function.py
ecmpy/ECMpy_function.py
ecmpy/__init__.py
ecmpy/get_ecGEM_onestop.py
ecmpy/model.py
ecmpy/prediction_for_input.py
ecmpy/_cache/ncbi_taxonomy/Acanthamoeba castellanii_taxonomy
ecmpy/_cache/ncbi_taxonomy/Acetivibrio clariflavus_taxonomy
ecmpy/_cache/ncbi_taxonomy/Acetivibrio thermocellus_taxonomy
ecmpy/_cache/ncbi_taxonomy/Acetobacter aceti_taxonomy
ecmpy/_cache/ncbi_taxonomy/Acetobacter xylinus_taxonomy_NA
ecmpy/_cache/ncbi_taxonomy/Acetobacter_taxonomy
ecmpy/_cache/ncbi_taxonomy/Acetomicrobium mobile_taxonomy
ecmpy/_cache/ncbi_taxonomy/Acholeplasma laidlawii_taxonomy
ecmpy/_cache/ncbi_taxonomy/Acidilobus saccharovorans_taxonomy
ecmpy/_cache/ncbi_taxonomy/Acidithiobacillus ferrooxidans_taxonomy
ecmpy/_cache/ncbi_taxonomy/Acidithiobacillus thiooxidans_taxonomy
ecmpy/_cache/ncbi_taxonomy/Acinetobacter baumannii_taxonomy
ecmpy/_cache/ncbi_taxonomy/Acinetobacter baylyi_taxonomy
ecmpy/_cache/ncbi_taxonomy/Acinetobacter calcoaceticus (subsp. anitratus)_taxonomy_NA
ecmpy/_cache/ncbi_taxonomy/Acinetobacter calcoaceticus subsp. anitratus_taxonomy
ecmpy/_cache/ncbi_taxonomy/Acinetobacter calcoaceticus_taxonomy
ecmpy/_cache/ncbi_taxonomy/Acinetobacter sp._taxonomy
ecmpy/_cache/ncbi_taxonomy/Actinidia chinensis_taxonomy
ecmpy/_cache/ncbi_taxonomy/Actinomadura sp. R39_taxonomy
ecmpy/_cache/ncbi_taxonomy/Actinomadura sp._taxonomy
ecmpy/_cache/ncbi_taxonomy/Actinoplanes missouriensis_taxonomy
ecmpy/_cache/ncbi_taxonomy/Actinosynnema pretiosum subsp. auranticum_taxonomy
ecmpy/_cache/ncbi_taxonomy/Advenella mimigardefordensis_taxonomy
ecmpy/_cache/ncbi_taxonomy/Aedes aegypti_taxonomy
ecmpy/_cache/ncbi_taxonomy/Aeribacillus pallidus_taxonomy
ECMpy-2.15.dist-info/METADATA
ECMpy-2.15.dist-info/WHEEL
ECMpy-2.15.dist-info/top_level.txt
ECMpy-2.15.dist-info/RECORD
